src/neuron.v
module neuron (
    input in1, in2, in3, in4,
    output reg detect
);

// neuron states (memory)
reg s1 = 0;
reg s2 = 0;
reg s3 = 0;

//
// 🔥 EVENT-DRIVEN LOGIC (NO CLOCK)
//
always @(in1 or in2 or in3 or in4) begin
    detect = 0;

    // Stage 1
    if (in1) begin
        s1 = 1;
    end

    // Stage 2
    if (in2 && s1) begin
        s2 = 1;
    end

    // Stage 3
    if (in3 && s2) begin
        s3 = 1;
    end

    // Final detection
    if (in4 && s3) begin
        detect = 1;

        // reset after detection
        s1 = 0;
        s2 = 0;
        s3 = 0;
    end

    // ❌ optional reset on invalid spike
    if (in2 && !s1) begin
        s2 = 0;
        s3 = 0;
    end

    if (in3 && !s2) begin
        s3 = 0;
    end
end

endmodule

`timescale 1ns/1ps

module testbench_snn;


reg in1, in2, in3, in4;
wire detect;

// Instantiate FSM
neuron uut (
    
    .in1(in1),
    .in2(in2),
    .in3(in3),
    .in4(in4),
    .detect(detect)
);

//
// 🔥 CLOCK (10ns period → 100 MHz)
//


//
// 🔥 MAIN STIMULUS
//
initial begin
  
    in1 = 0; in2 = 0; in3 = 0; in4 = 0;

    // =========================
    // 💤 LONG IDLE (SPARSITY)
    // =========================
    repeat (5000) begin
        in1 = 0; in2 = 0; in3 = 0; in4 = 0;
        #10;
    end

    // =========================
    // 🌪 RANDOM NOISE
    // =========================
    repeat (2000) begin
        in1 = $random % 2;
        in2 = $random % 2;
        in3 = $random % 2;
        in4 = $random % 2;
        #10;
    end

    // =========================
    // 🎯 VALID SEQUENCE (RARE)
    // =========================
    in1 = 1; in2 = 0; in3 = 0; in4 = 0; #10;
    in1 = 0; in2 = 1; in3 = 0; in4 = 0; #10;
    in1 = 0; in2 = 0; in3 = 1; in4 = 0; #10;
    in1 = 0; in2 = 0; in3 = 0; in4 = 1; #10;

    // =========================
    // 💤 MORE IDLE
    // =========================
    repeat (5000) begin
        in1 = 0; in2 = 0; in3 = 0; in4 = 0;
        #10;
    end

    // =========================
    // 🎯 ANOTHER VALID SEQUENCE
    // =========================
    in1 = 1; #10;
    in1 = 0; in2 = 1; #10;
    in2 = 0; in3 = 1; #10;
    in3 = 0; in4 = 1; #10;
    in4 = 0;

    // =========================
    // 🌪 LIGHT NOISE (SPARSE)
    // =========================
    repeat (1000) begin
        in1 = ($random % 10 == 0); // very rare spikes
        in2 = ($random % 12 == 0);
        in3 = ($random % 15 == 0);
        in4 = ($random % 18 == 0);
        #10;
    end

    $finish;
end

//
// 🔥 VCD DUMP (CRITICAL)
//
initial begin
    $dumpfile("snn_dump.vcd");
    $dumpvars(0, testbench_snn);
end

endmodule

snn_dump.vcd
$date
	Thu Apr 09 23:23:52 2026
$end
$version
	ModelSim Version 2020.1
$end
$timescale
	1ps
$end

$scope module testbench_snn $end
$var reg 1 ! in1 $end
$var reg 1 " in2 $end
$var reg 1 # in3 $end
$var reg 1 $ in4 $end
$var wire 1 % detect $end

$scope module uut $end
$var wire 1 & in1 $end
$var wire 1 ' in2 $end
$var wire 1 ( in3 $end
$var wire 1 ) in4 $end
$var reg 1 * detect $end
$var reg 1 + s1 $end
$var reg 1 , s2 $end
$var reg 1 - s3 $end
$upscope $end
$upscope $end
$enddefinitions $end
#0
$dumpvars
0!
0"
0#
0$
0*
0+
0,
0-
0%
0)
0(
0'
0&
$end
#50000000
1"
1#
1$
1'
1(
1)
#50010000
1!
0$
1&
0)
1+
1,
1-
#50020000
0#
1$
0(
1)
1*
0+
0,
0-
1%
#50030000
0"
1#
0$
0'
1(
0)
0*
1+
0%
#50040000
1$
1)
#50050000
0!
1"
0#
0$
0&
1'
0(
0)
1,
#50060000
1$
1)
#50070000
1!
1#
0$
1&
1(
0)
1-
#50080000
0!
0"
0#
1$
0&
0'
0(
1)
1*
0+
0,
0-
1%
#50090000
1"
1#
1'
1(
0*
0%
#50100000
1!
0#
0$
1&
0(
0)
1+
1,
#50110000
1#
1(
1-
#50120000
0!
0"
0#
0&
0'
0(
#50130000
1!
1$
1&
1)
1*
0+
0,
0-
1%
#50140000
0$
0)
0*
1+
0%
#50150000
0!
1#
1$
0&
1(
1)
#50160000
1!
1"
0$
1&
1'
0)
1,
1-
#50170000
0!
1$
0&
1)
1*
0+
0,
0-
1%
#50180000
0"
0'
0*
0%
#50190000
1"
0$
1'
0)
#50200000
1!
1&
1+
1,
1-
#50210000
0#
0(
#50220000
0!
0"
1#
1$
0&
0'
1(
1)
1*
0+
0,
0-
1%
#50240000
1!
1"
0$
1&
1'
0)
0*
1+
1,
1-
0%
#50260000
0!
0"
0#
0&
0'
0(
#50270000
1#
1$
1(
1)
1*
0+
0,
0-
1%
#50280000
1!
1"
0$
1&
1'
0)
0*
1+
1,
1-
0%
#50290000
0#
0(
#50300000
1$
1)
1*
0+
0,
0-
1%
#50310000
1#
0$
1(
0)
0*
1+
1,
1-
0%
#50320000
0!
0"
0&
0'
#50330000
1$
1)
1*
0+
0,
0-
1%
#50340000
0$
0)
0*
0%
#50360000
1"
0#
1$
1'
0(
1)
#50370000
1!
1#
1&
1(
1+
1,
1-
1*
0+
0,
0-
1%
#50380000
0!
0"
0#
0&
0'
0(
0*
0%
#50390000
1#
1(
#50400000
0#
0(
#50410000
1!
0$
1&
0)
1+
#50420000
1"
1'
1,
#50430000
0!
0&
#50440000
1!
0"
1&
0'
#50450000
1#
1$
1(
1)
1-
1*
0+
0,
0-
1%
#50460000
0!
0#
0$
0&
0(
0)
0*
0%
#50470000
1!
1&
1+
#50480000
0!
1"
1#
1$
0&
1'
1(
1)
1,
1-
1*
0+
0,
0-
1%
#50500000
0"
0'
0*
0%
#50510000
1!
1"
0$
1&
1'
0)
1+
1,
1-
#50520000
0#
0(
#50530000
0!
0"
1#
1$
0&
0'
1(
1)
1*
0+
0,
0-
1%
#50540000
0$
0)
0*
0%
#50550000
1"
0#
1'
0(
#50560000
1!
0"
1$
1&
0'
1)
1+
#50570000
1"
0$
1'
0)
1,
#50580000
0!
0&
#50590000
1!
0"
1&
0'
#50600000
0!
1"
0&
1'
#50610000
1#
1(
1-
#50620000
1!
1$
1&
1)
1*
0+
0,
0-
1%
#50630000
0!
0&
0*
0%
#50640000
0"
0$
0'
0)
#50650000
1"
1'
#50660000
0#
0(
#50670000
1!
0"
1#
1$
1&
0'
1(
1)
1+
#50680000
0!
1"
0#
0&
1'
0(
1,
#50690000
0"
1#
0$
0'
1(
0)
1-
#50700000
1$
1)
1*
0+
0,
0-
1%
#50710000
1!
1"
0$
1&
1'
0)
0*
1+
1,
1-
0%
#50730000
0!
0"
0#
0&
0'
0(
#50740000
1"
1#
1$
1'
1(
1)
1*
0+
0,
0-
1%
#50750000
1!
1&
0*
1+
1,
1-
1*
0+
0,
0-
#50760000
0!
0&
0*
0%
#50770000
1!
1&
1+
1,
1-
1*
0+
0,
0-
1%
#50780000
0"
0#
0'
0(
0*
1+
0%
#50790000
0$
0)
#50800000
0!
1"
0&
1'
1,
#50810000
0"
0'
#50820000
1!
1$
1&
1)
#50830000
0!
0$
0&
0)
#50840000
1!
1"
1#
1$
1&
1'
1(
1)
1-
1*
0+
0,
0-
1%
#50850000
0"
0'
0*
1+
0%
#50860000
0$
0)
#50870000
0!
1"
0&
1'
1,
1-
#50880000
1!
0"
0#
1$
1&
0'
0(
1)
1*
0+
0,
0-
1%
#50890000
0!
0$
0&
0)
0*
0%
#50900000
1!
1"
1#
1$
1&
1'
1(
1)
1+
1,
1-
1*
0+
0,
0-
1%
#50910000
0!
0&
0*
0%
#50920000
1!
1&
1+
1,
1-
1*
0+
0,
0-
1%
#50930000
0!
0#
0&
0(
0*
0%
#50940000
0"
1#
0$
0'
1(
0)
#50950000
0#
0(
#50960000
1!
1&
1+
#50970000
0!
1$
0&
1)
#50980000
1"
0$
1'
0)
1,
#50990000
1!
0"
1#
1$
1&
0'
1(
1)
1-
1*
0+
0,
0-
1%
#51000000
0!
1"
0#
0&
1'
0(
0*
0%
#51010000
0"
0$
0'
0)
#51020000
1!
1#
1&
1(
1+
#51030000
1"
0#
1$
1'
0(
1)
1,
#51040000
0!
1#
0&
1(
1-
1*
0+
0,
0-
1%
#51050000
0$
0)
0*
0%
#51080000
0#
0(
#51090000
1!
1&
1+
1,
#51100000
0"
1$
0'
1)
#51110000
1#
0$
1(
0)
1-
#51120000
1"
0#
1$
1'
0(
1)
1*
0+
0,
0-
1%
#51140000
0$
0)
0*
1+
1,
0%
#51150000
0"
1$
0'
1)
#51160000
0!
1#
0&
1(
1-
1*
0+
0,
0-
1%
#51170000
1"
0#
1'
0(
0*
0%
#51180000
1!
1#
0$
1&
1(
0)
1+
1,
1-
#51190000
0!
0#
1$
0&
0(
1)
1*
0+
0,
0-
1%
#51200000
1#
0$
1(
0)
0*
0%
#51210000
1$
1)
#51220000
0"
0$
0'
0)
#51230000
1"
1$
1'
1)
#51240000
0$
0)
#51250000
0"
1$
0'
1)
#51260000
1!
0#
0$
1&
0(
0)
1+
#51270000
1"
1#
1$
1'
1(
1)
1,
1-
1*
0+
0,
0-
1%
#51280000
0!
0&
0*
0%
#51290000
1!
1&
1+
1,
1-
1*
0+
0,
0-
1%
#51300000
0!
0#
0$
0&
0(
0)
0*
0%
#51310000
1#
1$
1(
1)
#51320000
1!
1&
1+
1,
1-
1*
0+
0,
0-
1%
#51330000
0#
0$
0(
0)
0*
1+
1,
0%
#51340000
0!
0&
#51350000
1#
1(
1-
#51360000
0"
1$
0'
1)
1*
0+
0,
0-
1%
#51370000
1"
0#
1'
0(
0*
0%
#51380000
0"
0'
#51390000
1!
1"
1&
1'
1+
1,
#51400000
0!
0&
#51410000
1!
0"
0$
1&
0'
0)
#51420000
0!
1"
1#
0&
1'
1(
1-
#51430000
0#
1$
0(
1)
1*
0+
0,
0-
1%
#51440000
1#
0$
1(
0)
0*
0%
#51450000
1!
0#
1&
0(
1+
1,
#51460000
0!
0"
1#
1$
0&
0'
1(
1)
1-
1*
0+
0,
0-
1%
#51470000
1!
1"
0$
1&
1'
0)
0*
1+
1,
1-
0%
#51480000
0!
0"
0#
0&
0'
0(
#51490000
1#
1$
1(
1)
1*
0+
0,
0-
1%
#51500000
1!
1"
1&
1'
0*
1+
1,
1-
1*
0+
0,
0-
#51510000
0"
0#
0$
0'
0(
0)
0*
1+
0%
#51520000
0!
1$
0&
1)
#51530000
1!
1#
0$
1&
1(
0)
#51540000
1"
1'
1,
1-
#51550000
0!
0"
1$
0&
0'
1)
1*
0+
0,
0-
1%
#51560000
1"
0#
0$
1'
0(
0)
0*
0%
#51570000
0"
0'
#51580000
1!
1$
1&
1)
1+
#51590000
0!
1#
0&
1(
#51600000
1!
0#
1&
0(
#51610000
1"
1#
0$
1'
1(
0)
1,
1-
#51620000
1$
1)
1*
0+
0,
0-
1%
#51630000
0!
0#
0$
0&
0(
0)
0*
0%
#51640000
1!
0"
1$
1&
0'
1)
1+
#51650000
0!
0$
0&
0)
#51660000
1#
1$
1(
1)
#51680000
1!
1"
1&
1'
1,
1-
1*
0+
0,
0-
1%
#51690000
0"
0$
0'
0)
0*
1+
0%
#51700000
0!
1$
0&
1)
#51710000
1"
1'
1,
1-
1*
0+
0,
0-
1%
#51720000
0"
0#
0$
0'
0(
0)
0*
0%
#51730000
1!
1"
1#
1&
1'
1(
1+
1,
1-
#51740000
0"
0#
0'
0(
#51750000
0!
0&
#51760000
1!
1$
1&
1)
1*
0+
0,
0-
1%
#51770000
1"
1#
1'
1(
0*
1+
1,
1-
1*
0+
0,
0-
#51780000
0!
0"
0#
0$
0&
0'
0(
0)
0*
0%
#51790000
1!
1"
1&
1'
1+
1,
#51800000
1#
1$
1(
1)
1-
1*
0+
0,
0-
1%
#51810000
0"
0#
0$
0'
0(
0)
0*
1+
0%
#51820000
1#
1(
#51830000
0!
0#
0&
0(
#51840000
1!
1#
1$
1&
1(
1)
#51850000
0!
1"
0$
0&
1'
0)
1,
1-
#51860000
1!
0"
1$
1&
0'
1)
1*
0+
0,
0-
1%
#51870000
0!
0&
0*
0%
#51880000
0#
0$
0(
0)
#51890000
1!
1"
1#
1&
1'
1(
1+
1,
1-
#51900000
0!
1$
0&
1)
1*
0+
0,
0-
1%
#51910000
1!
0"
0#
1&
0'
0(
0*
1+
0%
#51930000
0!
1"
0&
1'
1,
#51940000
1!
0"
0$
1&
0'
0)
#51950000
0!
1#
0&
1(
1-
#51960000
1!
0#
1&
0(
#51970000
1$
1)
1*
0+
0,
0-
1%
#51980000
0!
1"
1#
0&
1'
1(
0*
0%
#51990000
1!
0#
1&
0(
1+
1,
#52000000
0"
0'
#52010000
0!
1"
1#
0&
1'
1(
1-
1*
0+
0,
0-
1%
#52020000
1!
0#
1&
0(
0*
1+
1,
0%
#52030000
0!
0&
#52040000
1!
0"
0$
1&
0'
0)
#52050000
0!
1"
1#
0&
1'
1(
1-
#52060000
1$
1)
1*
0+
0,
0-
1%
#52070000
1!
0#
0$
1&
0(
0)
0*
1+
1,
0%
#52080000
0!
0"
1#
0&
0'
1(
1-
#52090000
1"
0#
1$
1'
0(
1)
1*
0+
0,
0-
1%
#52100000
0"
1#
0$
0'
1(
0)
0*
0%
#52110000
0#
1$
0(
1)
#52120000
1"
1#
0$
1'
1(
0)
#52130000
0#
1$
0(
1)
#52140000
1!
1#
0$
1&
1(
0)
1+
1,
1-
#52150000
0"
0#
1$
0'
0(
1)
1*
0+
0,
0-
1%
#52160000
1"
1'
0*
1+
1,
0%
#52170000
1#
1(
1-
1*
0+
0,
0-
1%
#52180000
0"
0$
0'
0)
0*
1+
0%
#52190000
0!
0&
#52200000
1!
1&
#52210000
0!
0#
1$
0&
0(
1)
#52220000
1#
0$
1(
0)
#52230000
1!
0#
1$
1&
0(
1)
#52250000
1#
1(
#52260000
1"
0#
1'
0(
1,
#52270000
0!
0"
1#
0&
0'
1(
1-
1*
0+
0,
0-
1%
#52280000
1"
0$
1'
0)
0*
0%
#52290000
1!
1&
1+
1,
1-
#52300000
0"
0'
#52310000
0!
0#
0&
0(
#52330000
1!
1"
1#
1&
1'
1(
#52340000
0!
0"
1$
0&
0'
1)
1*
0+
0,
0-
1%
#52350000
1"
1'
0*
0%
#52360000
0"
0'
#52370000
0#
0$
0(
0)
#52380000
1!
1#
1$
1&
1(
1)
1+
#52390000
0!
1"
0#
0&
1'
0(
1,
#52400000
1!
0"
1#
1&
0'
1(
1-
1*
0+
0,
0-
1%
#52410000
1"
0#
1'
0(
0*
1+
1,
0%
#52420000
0!
0$
0&
0)
#52430000
0"
1#
0'
1(
1-
#52440000
1!
0#
1$
1&
0(
1)
1*
0+
0,
0-
1%
#52450000
1"
1#
0$
1'
1(
0)
0*
1+
1,
1-
0%
#52470000
0!
1$
0&
1)
1*
0+
0,
0-
1%
#52480000
0$
0)
0*
0%
#52490000
0#
0(
#52500000
1!
1&
1+
1,
#52510000
0"
0'
#52520000
1"
1#
1$
1'
1(
1)
1-
1*
0+
0,
0-
1%
#52530000
0#
0(
0*
1+
1,
0%
#52540000
0!
0&
#52570000
0"
0'
#52580000
1#
1(
1-
1*
0+
0,
0-
1%
#52590000
1!
1"
0$
1&
1'
0)
0*
1+
1,
1-
0%
#52600000
0#
1$
0(
1)
1*
0+
0,
0-
1%
#52610000
0!
1#
0&
1(
0*
0%
#52620000
1!
0#
1&
0(
1+
1,
#52630000
0!
1#
0&
1(
1-
1*
0+
0,
0-
1%
#52640000
1!
0"
1&
0'
0*
1+
0%
#52650000
1"
0#
0$
1'
0(
0)
1,
#52660000
0!
1#
0&
1(
1-
#52670000
0"
1$
0'
1)
1*
0+
0,
0-
1%
#52680000
1!
0#
1&
0(
0*
1+
0%
#52690000
0!
0$
0&
0)
#52700000
1#
1$
1(
1)
#52710000
0#
0$
0(
0)
#52720000
1"
1#
1$
1'
1(
1)
1,
1-
1*
0+
0,
0-
1%
#52730000
1!
0#
0$
1&
0(
0)
0*
1+
1,
0%
#52740000
0!
0"
1#
1$
0&
0'
1(
1)
1-
1*
0+
0,
0-
1%
#52750000
1!
1"
0$
1&
1'
0)
0*
1+
1,
1-
0%
#52760000
0!
0"
0&
0'
#52780000
1!
1"
1$
1&
1'
1)
1*
0+
0,
0-
1%
#52790000
0!
0"
0#
0&
0'
0(
0*
0%
#52800000
1!
1"
0$
1&
1'
0)
1+
1,
#52810000
0!
0"
1$
0&
0'
1)
#52820000
1!
1"
0$
1&
1'
0)
#52830000
0!
1$
0&
1)
#52840000
1#
1(
1-
1*
0+
0,
0-
1%
#52850000
1!
0"
1&
0'
0*
1+
0%
#52860000
0!
0$
0&
0)
#52880000
1"
0#
1$
1'
0(
1)
1,
#52890000
1!
1&
#52900000
0!
1#
0&
1(
1-
1*
0+
0,
0-
1%
#52910000
0"
0#
0$
0'
0(
0)
0*
0%
#52920000
1$
1)
#52930000
1!
1"
1#
1&
1'
1(
1+
1,
1-
1*
0+
0,
0-
1%
#52940000
0#
0$
0(
0)
0*
1+
1,
0%
#52950000
1#
1(
1-
#52960000
0#
1$
0(
1)
1*
0+
0,
0-
1%
#52970000
0!
1#
0&
1(
0*
0%
#52980000
0#
0(
#52990000
1!
0"
0$
1&
0'
0)
1+
#53010000
0!
1#
0&
1(
#53030000
1!
1"
0#
1$
1&
1'
0(
1)
1,
#53040000
0!
0"
0$
0&
0'
0)
#53050000
1!
1"
1#
1$
1&
1'
1(
1)
1-
1*
0+
0,
0-
1%
#53060000
0!
0"
0$
0&
0'
0)
0*
0%
#53070000
1!
1"
1&
1'
1+
1,
1-
#53080000
0#
1$
0(
1)
1*
0+
0,
0-
1%
#53090000
1#
0$
1(
0)
0*
1+
1,
1-
0%
#53100000
0!
0"
1$
0&
0'
1)
1*
0+
0,
0-
1%
#53110000
1!
0$
1&
0)
0*
1+
0%
#53120000
0!
1"
0&
1'
1,
1-
#53130000
0#
1$
0(
1)
1*
0+
0,
0-
1%
#53140000
1#
0$
1(
0)
0*
0%
#53150000
1!
1&
1+
1,
1-
#53160000
0!
0"
0&
0'
#53170000
1"
0#
1'
0(
#53180000
1!
0"
1$
1&
0'
1)
1*
0+
0,
0-
1%
#53190000
0$
0)
0*
1+
0%
#53200000
1"
1$
1'
1)
1,
#53210000
0"
1#
0$
0'
1(
0)
1-
#53220000
1"
1'
#53230000
0#
1$
0(
1)
1*
0+
0,
0-
1%
#53240000
0!
0$
0&
0)
0*
0%
#53250000
1!
1#
1$
1&
1(
1)
1+
1,
1-
1*
0+
0,
0-
1%
#53260000
0!
0"
0&
0'
0*
0%
#53270000
1!
0#
1&
0(
1+
#53280000
1#
1(
#53290000
1"
0#
1'
0(
1,
#53300000
0!
0"
0&
0'
#53310000
1#
0$
1(
0)
1-
#53320000
1!
0#
1&
0(
#53340000
1"
1$
1'
1)
1*
0+
0,
0-
1%
#53350000
0"
0$
0'
0)
0*
1+
0%
#53360000
1#
1$
1(
1)
#53370000
0!
1"
0#
0&
1'
0(
1,
#53390000
1!
0"
1#
1&
0'
1(
1-
1*
0+
0,
0-
1%
#53400000
0!
1"
0#
0&
1'
0(
0*
0%
#53410000
0"
1#
0$
0'
1(
0)
#53430000
0#
0(
#53440000
1#
1$
1(
1)
#53450000
1!
0#
1&
0(
1+
#53460000
0!
1"
1#
0&
1'
1(
1,
1-
1*
0+
0,
0-
1%
#53470000
1!
0#
0$
1&
0(
0)
0*
1+
1,
0%
#53480000
0!
0"
1$
0&
0'
1)
#53490000
1!
1"
1#
0$
1&
1'
1(
0)
1-
#53500000
0!
0"
1$
0&
0'
1)
1*
0+
0,
0-
1%
#53510000
1!
0$
1&
0)
0*
1+
0%
#53520000
0#
0(
#53530000
0!
0&
#53540000
1$
1)
#53550000
1!
1"
1#
1&
1'
1(
1,
1-
1*
0+
0,
0-
1%
#53560000
0!
0"
0&
0'
0*
0%
#53570000
1"
0#
1'
0(
#53580000
0"
0$
0'
0)
#53590000
1!
1"
1#
1&
1'
1(
1+
1,
1-
#53600000
0#
1$
0(
1)
1*
0+
0,
0-
1%
#53610000
0!
0"
0&
0'
0*
0%
#53620000
1!
1&
1+
#53630000
1"
1#
1'
1(
1,
1-
1*
0+
0,
0-
1%
#53640000
0!
0"
0#
0&
0'
0(
0*
0%
#53650000
1!
1#
0$
1&
1(
0)
1+
#53660000
1"
1'
1,
1-
#53670000
0"
0#
0'
0(
#53680000
0!
1"
1$
0&
1'
1)
1*
0+
0,
0-
1%
#53690000
1!
0"
0$
1&
0'
0)
0*
1+
0%
#53700000
1"
1$
1'
1)
1,
#53710000
0!
1#
0$
0&
1(
0)
1-
#53720000
1!
1&
#53730000
1$
1)
1*
0+
0,
0-
1%
#53740000
0!
0&
0*
0%
#53750000
1!
0#
1&
0(
1+
1,
#53770000
0!
1#
0$
0&
1(
0)
1-
#53780000
1!
0"
0#
1&
0'
0(
#53790000
0!
1"
1$
0&
1'
1)
1*
0+
0,
0-
1%
#53800000
1#
0$
1(
0)
0*
0%
#53810000
0#
1$
0(
1)
#53820000
1!
1#
0$
1&
1(
0)
1+
1,
1-
#53830000
0#
1$
0(
1)
1*
0+
0,
0-
1%
#53840000
0!
1#
0$
0&
1(
0)
0*
0%
#53850000
1!
0#
1&
0(
1+
1,
#53860000
0"
0'
#53870000
0!
1"
1#
1$
0&
1'
1(
1)
1-
1*
0+
0,
0-
1%
#53880000
0"
0$
0'
0)
0*
0%
#53900000
1"
0#
1'
0(
#53910000
1$
1)
#53920000
1!
1#
0$
1&
1(
0)
1+
1,
1-
#53930000
0!
0&
#53940000
1!
0"
0#
1$
1&
0'
0(
1)
1*
0+
0,
0-
1%
#53950000
0!
1"
1#
0&
1'
1(
0*
0%
#53960000
1!
0$
1&
0)
1+
1,
1-
#53970000
0"
0'
#53980000
1$
1)
1*
0+
0,
0-
1%
#53990000
0$
0)
0*
1+
0%
#54000000
0#
0(
#54010000
1"
1#
1'
1(
1,
1-
#54020000
0"
0#
1$
0'
0(
1)
1*
0+
0,
0-
1%
#54040000
0!
1"
0$
0&
1'
0)
0*
0%
#54050000
1!
1#
1$
1&
1(
1)
1+
1,
1-
1*
0+
0,
0-
1%
#54060000
0"
0$
0'
0)
0*
1+
0%
#54070000
0!
1"
0#
0&
1'
0(
1,
#54080000
1!
1&
#54090000
0!
1$
0&
1)
#54100000
1!
0"
1#
1&
0'
1(
1-
1*
0+
0,
0-
1%
#54110000
0!
1"
0&
1'
0*
0%
#54120000
0"
0'
#54130000
1"
0#
1'
0(
#54140000
1!
1#
0$
1&
1(
0)
1+
1,
1-
#54150000
0!
0"
1$
0&
0'
1)
1*
0+
0,
0-
1%
#54160000
1!
1"
0$
1&
1'
0)
0*
1+
1,
1-
0%
#54170000
0!
0"
0#
1$
0&
0'
0(
1)
1*
0+
0,
0-
1%
#54180000
1#
0$
1(
0)
0*
0%
#54190000
1"
1'
#54200000
1!
0"
1&
0'
1+
#54210000
0#
0(
#54220000
0!
1$
0&
1)
#54230000
1"
0$
1'
0)
1,
#54240000
1!
0"
1$
1&
0'
1)
#54260000
0!
0&
#54270000
0$
0)
#54280000
1"
1#
1'
1(
1-
#54290000
1!
0#
1&
0(
#54300000
0!
0"
0&
0'
#54310000
1"
1#
1'
1(
#54320000
1$
1)
1*
0+
0,
0-
1%
#54330000
1!
0"
0#
0$
1&
0'
0(
0)
0*
1+
0%
#54340000
0!
1"
1$
0&
1'
1)
1,
#54350000
1#
1(
1-
1*
0+
0,
0-
1%
#54360000
1!
0#
1&
0(
0*
1+
1,
0%
#54370000
0!
1#
0&
1(
1-
1*
0+
0,
0-
1%
#54380000
0"
0'
0*
0%
#54390000
1"
0$
1'
0)
#54410000
0#
1$
0(
1)
#54420000
1#
0$
1(
0)
#54430000
1!
1$
1&
1)
1+
1,
1-
1*
0+
0,
0-
1%
#54440000
0$
0)
0*
1+
1,
1-
0%
#54450000
1$
1)
1*
0+
0,
0-
1%
#54460000
0"
0'
0*
1+
0%
#54470000
1"
0#
0$
1'
0(
0)
1,
#54480000
1$
1)
#54490000
0"
1#
0$
0'
1(
0)
1-
#54510000
0!
0#
0&
0(
#54520000
1$
1)
1*
0+
0,
0-
1%
#54530000
1!
1#
0$
1&
1(
0)
0*
1+
0%
#54540000
0!
1"
1$
0&
1'
1)
1,
1-
1*
0+
0,
0-
1%
#54550000
1!
0"
0#
0$
1&
0'
0(
0)
0*
1+
0%
#54560000
1"
1#
1'
1(
1,
1-
#54570000
0!
0"
0&
0'
#54580000
1!
1$
1&
1)
1*
0+
0,
0-
1%
#54590000
0!
1"
0$
0&
1'
0)
0*
0%
#54600000
1!
0#
1&
0(
1+
1,
#54610000
0!
0"
1#
0&
0'
1(
1-
#54620000
0#
0(
#54630000
1#
1$
1(
1)
1*
0+
0,
0-
1%
#54640000
1!
1&
0*
1+
0%
#54650000
0!
0$
0&
0)
#54660000
0#
0(
#54670000
1!
1&
#54680000
1"
1#
1$
1'
1(
1)
1,
1-
1*
0+
0,
0-
1%
#54700000
0"
0$
0'
0)
0*
1+
0%
#54710000
0!
1"
1$
0&
1'
1)
1,
1-
1*
0+
0,
0-
1%
#54720000
0"
0$
0'
0)
0*
0%
#54730000
1"
0#
1'
0(
#54740000
0"
1$
0'
1)
#54750000
1!
1"
0$
1&
1'
0)
1+
1,
#54760000
0"
1#
1$
0'
1(
1)
1-
1*
0+
0,
0-
1%
#54770000
0$
0)
0*
1+
0%
#54780000
0!
0#
0&
0(
#54790000
1!
1"
1#
1$
1&
1'
1(
1)
1,
1-
1*
0+
0,
0-
1%
#54800000
0"
0#
0'
0(
0*
1+
0%
#54810000
1"
0$
1'
0)
1,
#54820000
0!
0"
0&
0'
#54830000
1!
1"
1$
1&
1'
1)
#54840000
0!
0"
1#
0$
0&
0'
1(
0)
1-
#54850000
0#
0(
#54860000
1#
1$
1(
1)
1*
0+
0,
0-
1%
#54870000
1!
1"
0#
1&
1'
0(
0*
1+
1,
0%
#54880000
0!
0"
0$
0&
0'
0)
#54890000
1!
1#
1&
1(
1-
#54900000
0!
1"
0&
1'
#54920000
1!
0"
1&
0'
#54930000
0!
1"
0#
1$
0&
1'
0(
1)
1*
0+
0,
0-
1%
#54940000
0"
1#
0$
0'
1(
0)
0*
0%
#54950000
1!
0#
1&
0(
1+
#54960000
0!
1$
0&
1)
#54970000
1!
0$
1&
0)
#54980000
1"
1#
1$
1'
1(
1)
1,
1-
1*
0+
0,
0-
1%
#54990000
0$
0)
0*
1+
1,
1-
0%
#55000000
0!
0#
1$
0&
0(
1)
1*
0+
0,
0-
1%
#55010000
1!
1#
0$
1&
1(
0)
0*
1+
1,
1-
0%
#55020000
1$
1)
1*
0+
0,
0-
1%
#55030000
0!
0#
0$
0&
0(
0)
0*
0%
#55040000
1#
1$
1(
1)
#55050000
0"
0$
0'
0)
#55060000
1"
0#
1'
0(
#55070000
0"
1#
0'
1(
#55080000
1"
0#
1$
1'
0(
1)
#55090000
0"
0$
0'
0)
#55100000
1!
1#
1$
1&
1(
1)
1+
#55110000
0!
1"
0&
1'
1,
1-
1*
0+
0,
0-
1%
#55120000
1!
0"
1&
0'
0*
1+
0%
#55130000
0!
0#
0$
0&
0(
0)
#55140000
1!
1"
1#
1$
1&
1'
1(
1)
1,
1-
1*
0+
0,
0-
1%
#55150000
0"
0$
0'
0)
0*
1+
0%
#55170000
0!
1$
0&
1)
#55180000
1"
0#
1'
0(
1,
#55190000
1!
1#
0$
1&
1(
0)
1-
#55200000
0!
0"
0&
0'
#55210000
1!
0#
1$
1&
0(
1)
1*
0+
0,
0-
1%
#55220000
0!
1"
0$
0&
1'
0)
0*
0%
#55230000
1!
0"
1#
1&
0'
1(
1+
#55240000
0!
1"
1$
0&
1'
1)
1,
1-
1*
0+
0,
0-
1%
#55250000
1!
0"
1&
0'
0*
1+
0%
#55260000
0#
0$
0(
0)
#55270000
0!
1$
0&
1)
#55280000
0$
0)
#55290000
1!
1$
1&
1)
#55300000
0!
1"
0$
0&
1'
0)
1,
#55310000
1!
0"
1&
0'
#55320000
0!
1"
1$
0&
1'
1)
#55330000
0"
1#
0$
0'
1(
0)
1-
#55340000
1"
1$
1'
1)
1*
0+
0,
0-
1%
#55350000
0"
0'
0*
0%
#55360000
1!
1&
1+
#55370000
1"
0#
0$
1'
0(
0)
1,
#55380000
0!
0"
1#
1$
0&
0'
1(
1)
1-
1*
0+
0,
0-
1%
#55390000
1!
1&
0*
1+
0%
#55400000
0!
0#
0$
0&
0(
0)
#55410000
1"
1'
1,
#55420000
0"
0'
#55440000
1#
1(
1-
#55450000
0#
0(
#55460000
1!
1"
1&
1'
#55470000
1$
1)
1*
0+
0,
0-
1%
#55480000
0!
0"
0$
0&
0'
0)
0*
0%
#55490000
1!
1"
1$
1&
1'
1)
1+
1,
#55500000
1#
1(
1-
1*
0+
0,
0-
1%
#55510000
0!
0"
0#
0$
0&
0'
0(
0)
0*
0%
#55520000
1!
1#
1$
1&
1(
1)
1+
#55530000
1"
0$
1'
0)
1,
1-
#55540000
0!
0"
0#
0&
0'
0(
#55550000
1"
1$
1'
1)
1*
0+
0,
0-
1%
#55570000
1!
0"
1&
0'
0*
1+
0%
#55580000
0!
1"
1#
0$
0&
1'
1(
0)
1,
1-
#55590000
0"
0#
0'
0(
#55600000
1!
1&
#55610000
0!
1"
1#
0&
1'
1(
#55620000
1!
0"
0#
1&
0'
0(
#55630000
0!
1"
1$
0&
1'
1)
1*
0+
0,
0-
1%
#55640000
0$
0)
0*
0%
#55650000
1!
0"
1#
1&
0'
1(
1+
#55660000
0!
1$
0&
1)
#55670000
1!
0$
1&
0)
#55680000
1$
1)
#55690000
0$
0)
#55700000
0!
1"
0#
1$
0&
1'
0(
1)
1,
#55710000
1!
0"
0$
1&
0'
0)
#55720000
0!
1"
1#
0&
1'
1(
1-
#55730000
1!
0"
1$
1&
0'
1)
1*
0+
0,
0-
1%
